{"3":{"inputs":{"ckpt_name":"realisticVisionV60B1_v51HyperVAE.safetensors"},"class_type":"CheckpointLoaderSimple","_meta":{"title":"Checkpoint加载器(简易)"}},"4":{"inputs":{"text":["122",0],"clip":["13",1]},"class_type":"CLIPTextEncode","_meta":{"title":"CLIP文本编码器"}},"5":{"inputs":{"text":["123",0],"clip":["13",1]},"class_type":"CLIPTextEncode","_meta":{"title":"CLIP文本编码器"}},"13":{"inputs":{"lora_name":"UIAxd1.0.safetensors","strength_model":0.3,"strength_clip":1,"model":["3",0],"clip":["3",1]},"class_type":"LoraLoader","_meta":{"title":"LoRA加载器"}},"29":{"inputs":{"seed":1067903296018912,"steps":8,"cfg":2.4,"sampler_name":"lcm","scheduler":"exponential","denoise":0.4,"model":["13",0],"positive":["41",0],"negative":["41",1],"latent_image":["40",0]},"class_type":"KSampler","_meta":{"title":"K采样器"}},"34":{"inputs":{"samples":["29",0],"vae":["3",2]},"class_type":"VAEDecode","_meta":{"title":"VAE解码"}},"36":{"inputs":{"upscale_model":["37",0],"image":["89",5]},"class_type":"ImageUpscaleWithModel","_meta":{"title":"图像通过模型放大"}},"37":{"inputs":{"model_name":"4x-UltraSharp.pth"},"class_type":"Upscale Model Loader","_meta":{"title":"放大模型加载器"}},"39":{"inputs":{"upscale_method":"nearest-exact","scale_by":0.5,"image":["36",0]},"class_type":"ImageScaleBy","_meta":{"title":"图像按系数缩放"}},"40":{"inputs":{"pixels":["39",0],"vae":["3",2]},"class_type":"VAEEncode","_meta":{"title":"VAE编码"}},"41":{"inputs":{"strength":0.45,"start_percent":0,"end_percent":1,"positive":["4",0],"negative":["5",0],"control_net":["42",0],"image":["43",0]},"class_type":"ControlNetApplyAdvanced","_meta":{"title":"ControlNet应用(高级)"}},"42":{"inputs":{"control_net_name":"control_v11f1e_sd15_tile_fp16.safetensors"},"class_type":"ControlNetLoaderAdvanced","_meta":{"title":"ControlNet加载器(高级)"}},"43":{"inputs":{"pyrUp_iters":2,"resolution":512,"image":["39",0]},"class_type":"TilePreprocessor","_meta":{"title":"Tile平铺预处理器"}},"89":{"inputs":{"seed":1067903296018912,"steps":7,"cfg":4,"sampler_name":"dpmpp_sde_gpu","scheduler":"karras","denoise":1,"preview_method":"none","vae_decode":"true","model":["13",0],"positive":["114",0],"negative":["114",1],"latent_image":["104",0],"optional_vae":["3",2]},"class_type":"KSampler (Efficient)","_meta":{"title":"K采样器(效率)"}},"104":{"inputs":{"pixels":["144",0],"vae":["3",2]},"class_type":"VAEEncode","_meta":{"title":"VAE编码"}},"106":{"inputs":{"control_net_name":"control_v11p_sd15_scribble_fp16.safetensors"},"class_type":"ControlNetLoader","_meta":{"title":"ControlNet加载器"}},"107":{"inputs":{"strength":1,"start_percent":0,"end_percent":1,"positive":["4",0],"negative":["5",0],"control_net":["106",0],"image":["130",0]},"class_type":"ControlNetApplyAdvanced","_meta":{"title":"ControlNet应用(高级)"}},"113":{"inputs":{"control_net_name":"control_v11p_sd15_seg_fp16.safetensors"},"class_type":"ControlNetLoader","_meta":{"title":"ControlNet加载器"}},"114":{"inputs":{"strength":0.2,"start_percent":0,"end_percent":1,"positive":["107",0],"negative":["107",1],"control_net":["113",0],"image":["140",0]},"class_type":"ControlNetApplyAdvanced","_meta":{"title":"ControlNet应用(高级)"}},"120":{"inputs":{"image":"123 (1).png","upload":"image"},"class_type":"LoadImage","_meta":{"title":"加载图像"}},"122":{"inputs":{"from_translate":"auto","to_translate":"en","manual_translate":false,"Manual Trasnlate":"Manual Trasnlate","text":"White villa,cottages,Design sense, masterpiece,landscape,Hyperreal, (real world),best qualitymasterpiece, absurdres, best quality, (photo realistic:1.5), hyper detailed photo,architecture, building, vivid colour, masterpiece,best quality,super detailed,realistic,photorealistic, 8k,sharp  "},"class_type":"GoogleTranslateTextNode","_meta":{"title":"Google Translate Text Node Positive"}},"123":{"inputs":{"from_translate":"auto","to_translate":"en","manual_translate":true,"Manual Trasnlate":"Manual Trasnlate","text":"watermarks,word,blur,bad anatomy, bad hands, text, error, missing fingers, extra digit, fewer digits, cropped, worst quality, low quality, normal quality, jpeg artifacts, signature, watermark, username, blurry, lowres, text, cropped, worst quality, low quality, normal quality, jpeg artifacts, signature, watermark, username, blurry, text, signature, watermark, simple background,  low res, line art, flat colors\n"},"class_type":"GoogleTranslateTextNode","_meta":{"title":"Google Translate Text Node Negative"}},"124":{"inputs":{"upscale_method":"nearest-exact","scale_by":1,"image":["120",0]},"class_type":"ImageScaleBy","_meta":{"title":"图像按系数缩放"}},"130":{"inputs":{"preprocessor":"Scribble_XDoG_Preprocessor","resolution":512,"image":["144",0]},"class_type":"AIO_Preprocessor","_meta":{"title":"Aux集成预处理器"}},"140":{"inputs":{"preprocessor":"SemSegPreprocessor","resolution":512,"image":["144",0]},"class_type":"AIO_Preprocessor","_meta":{"title":"Aux集成预处理器"}},"144":{"inputs":{"width":1024,"height":512,"interpolation":"nearest","method":"keep proportion","condition":"always","multiple_of":0,"image":["120",0]},"class_type":"ImageResize+","_meta":{"title":"图像缩放"}},"146":{"inputs":{"images":["34",0]},"class_type":"SaveImageWebsocket","_meta":{"title":"保存图像到网络接口"}}}